LICENSE
MANIFEST.in
README.md
setup.cfg
setup.py
timm_ctp/__init__.py
timm_ctp/version.py
timm_ctp.egg-info/PKG-INFO
timm_ctp.egg-info/SOURCES.txt
timm_ctp.egg-info/dependency_links.txt
timm_ctp.egg-info/requires.txt
timm_ctp.egg-info/top_level.txt
timm_ctp/data/__init__.py
timm_ctp/data/auto_augment.py
timm_ctp/data/config.py
timm_ctp/data/constants.py
timm_ctp/data/dataset.py
timm_ctp/data/dataset_factory.py
timm_ctp/data/distributed_sampler.py
timm_ctp/data/loader.py
timm_ctp/data/mixup.py
timm_ctp/data/random_erasing.py
timm_ctp/data/real_labels.py
timm_ctp/data/tf_preprocessing.py
timm_ctp/data/transforms.py
timm_ctp/data/transforms_factory.py
timm_ctp/data/parsers/__init__.py
timm_ctp/data/parsers/class_map.py
timm_ctp/data/parsers/constants.py
timm_ctp/data/parsers/parser.py
timm_ctp/data/parsers/parser_factory.py
timm_ctp/data/parsers/parser_image_folder.py
timm_ctp/data/parsers/parser_image_in_tar.py
timm_ctp/data/parsers/parser_image_tar.py
timm_ctp/data/parsers/parser_tfds.py
timm_ctp/loss/__init__.py
timm_ctp/loss/asymmetric_loss.py
timm_ctp/loss/binary_cross_entropy.py
timm_ctp/loss/cross_entropy.py
timm_ctp/loss/jsd.py
timm_ctp/models/__init__.py
timm_ctp/models/beit.py
timm_ctp/models/byoanet.py
timm_ctp/models/byobnet.py
timm_ctp/models/cait.py
timm_ctp/models/coat.py
timm_ctp/models/convit.py
timm_ctp/models/convmixer.py
timm_ctp/models/convnext.py
timm_ctp/models/crossvit.py
timm_ctp/models/cspnet.py
timm_ctp/models/densenet.py
timm_ctp/models/dla.py
timm_ctp/models/dpn.py
timm_ctp/models/efficientnet.py
timm_ctp/models/efficientnet_blocks.py
timm_ctp/models/efficientnet_builder.py
timm_ctp/models/factory.py
timm_ctp/models/features.py
timm_ctp/models/fx_features.py
timm_ctp/models/ghostnet.py
timm_ctp/models/gluon_resnet.py
timm_ctp/models/gluon_xception.py
timm_ctp/models/hardcorenas.py
timm_ctp/models/helpers.py
timm_ctp/models/hrnet.py
timm_ctp/models/hub.py
timm_ctp/models/inception_resnet_v2.py
timm_ctp/models/inception_v3.py
timm_ctp/models/inception_v4.py
timm_ctp/models/levit.py
timm_ctp/models/mlp_mixer.py
timm_ctp/models/mobilenetv3.py
timm_ctp/models/nasnet.py
timm_ctp/models/nest.py
