Metadata-Version: 2.1
Name: timm_ctp
Version: 0.5.4
Summary: (Unofficial) PyTorch Image Models
Home-page: https://github.com/rwightman/pytorch-image-models
Author: Ross Wightman
Author-email: hello@rwightman.com
Keywords: pytorch pretrained models efficientnet mobilenetv3 mnasnet
Classifier: Development Status :: 3 - Alpha
Classifier: Intended Audience :: Education
Classifier: Intended Audience :: Science/Research
Classifier: License :: OSI Approved :: Apache Software License
Classifier: Programming Language :: Python :: 3.6
Classifier: Programming Language :: Python :: 3.7
Classifier: Programming Language :: Python :: 3.8
Classifier: Topic :: Scientific/Engineering
Classifier: Topic :: Scientific/Engineering :: Artificial Intelligence
Classifier: Topic :: Software Development
Classifier: Topic :: Software Development :: Libraries
Classifier: Topic :: Software Development :: Libraries :: Python Modules
Requires-Python: >=3.6
License-File: LICENSE
Requires-Dist: torch>=1.4
Requires-Dist: torchvision
